sktree/__init__.py
sktree/neighbors.py
sktree/tests/test_honest_forest.py
sktree/tests/test_neighbors.py
sktree/tests/__init__.py
sktree/tests/test_unsupervised_forest.py
sktree/tests/test_supervised_forest.py
sktree/tree/_neighbors.py
sktree/tree/_oblique_splitter.cpython-39-x86_64-linux-gnu.so
sktree/tree/_marginal.cpython-39-x86_64-linux-gnu.so
sktree/tree/__init__.py
sktree/tree/_classes.py
sktree/tree/_utils.cpython-39-x86_64-linux-gnu.so
sktree/tree/_sklearn_splitter.cpython-39-x86_64-linux-gnu.so
sktree/tree/_marginalize.py
sktree/tree/_honest_tree.py
sktree/tree/_oblique_tree.cpython-39-x86_64-linux-gnu.so
sktree/tree/tests/test_utils.py
sktree/tree/tests/__init__.py
sktree/tree/tests/test_tree.py
sktree/tree/tests/test_marginal.py
sktree/tree/tests/test_honest_tree.py
sktree/tree/manifold/_morf_splitter.cpython-39-x86_64-linux-gnu.so
sktree/tree/unsupervised/_unsup_tree.cpython-39-x86_64-linux-gnu.so
sktree/tree/unsupervised/_unsup_oblique_tree.cpython-39-x86_64-linux-gnu.so
sktree/tree/unsupervised/_unsup_splitter.cpython-39-x86_64-linux-gnu.so
sktree/tree/unsupervised/_unsup_criterion.cpython-39-x86_64-linux-gnu.so
sktree/tree/unsupervised/_unsup_oblique_splitter.cpython-39-x86_64-linux-gnu.so
sktree/ensemble/_honest_forest.py
sktree/ensemble/__init__.py
sktree/ensemble/_unsupervised_forest.py
sktree/ensemble/_supervised_forest.py
sktree/experimental/mutual_info.py
sktree/experimental/__init__.py
sktree/experimental/simulate.py
sktree/experimental/tests/__init__.py
sktree/experimental/tests/test_mutual_info.py
sktree/experimental/tests/test_simulate.py
sktree/_lib/sklearn/tree/_reingold_tilford.py
sktree/_lib/sklearn/tree/_splitter.cpython-39-x86_64-linux-gnu.so
sktree/_lib/sklearn/tree/__init__.py
sktree/_lib/sklearn/tree/_classes.py
sktree/_lib/sklearn/tree/_utils.cpython-39-x86_64-linux-gnu.so
sktree/_lib/sklearn/tree/_export.py
sktree/_lib/sklearn/tree/_tree.cpython-39-x86_64-linux-gnu.so
sktree-0.1.3.dist-info/METADATA
sktree-0.1.3.dist-info/WHEEL
sktree-0.1.3.dist-info/RECORD
